unrar2_cffi-0.4.1.dist-info/RECORD
unrar2_cffi-0.4.1.dist-info/WHEEL
unrar2_cffi-0.4.1.dist-info/top_level.txt
unrar2_cffi-0.4.1.dist-info/METADATA
unrar2_cffi-0.4.1.dist-info/licenses/LICENSE
unrar/cffi/unrarlib_py.h
unrar/cffi/unrarlib.py
unrar/cffi/unrarlib_ext.h
unrar/cffi/__init__.py
unrar/cffi/_unrarlib.abi3.so
unrar/cffi/unrarlib_ext.c
unrar/cffi/rarfile.py
