Metadata-Version: 2.4
Name: unrar2-cffi
Version: 0.4.1
Summary: Read RAR file from python -- cffi edition
Author-email: noaione <noaione@n4o.xyz>, Davide Romanini <davide.romanini@gmail.com>
License-Expression: Apache-2.0
Project-URL: homepage, https://github.com/noaione/unrar2-cffi
Project-URL: changelog, https://github.com/noaione/unrar2-cffi/blob/develop/CHANGELOG.md
Keywords: rar,unrar,archive,cffi
Classifier: Development Status :: 3 - Alpha
Classifier: Intended Audience :: Developers
Classifier: Topic :: Software Development :: Libraries
Classifier: Programming Language :: Python :: 3
Classifier: Programming Language :: Python :: 3.9
Classifier: Programming Language :: Python :: 3.10
Classifier: Programming Language :: Python :: 3.11
Classifier: Programming Language :: Python :: 3.12
Classifier: Programming Language :: Python :: 3.13
Requires-Python: >=3.9
License-File: LICENSE
Requires-Dist: cffi
Dynamic: license-file
